cataractseverity/__init__.py
cataractseverity/cataract.py
cataractseverity-0.0.1.dist-info/LICENSE
cataractseverity-0.0.1.dist-info/METADATA
cataractseverity-0.0.1.dist-info/WHEEL
cataractseverity-0.0.1.dist-info/top_level.txt
cataractseverity-0.0.1.dist-info/RECORD
