Metadata-Version: 2.1
Name: cataractseverity
Version: 0.0.1
Summary: Cataract Severity Detection Interface
Home-page: https://github.com/0xraia/cataract-severity.git
Author: Mamang Joko
Author-email: aimar.airdrop123@gmail.com
License: MIT
Project-URL: Source, https://github.com/0xraia/cataract-severity.git
Keywords: python,interface
License-File: LICENSE
Requires-Dist: opencv-python
Requires-Dist: tensorflow
Requires-Dist: camconnect
Requires-Dist: numpy
